<?xml version="1.0" encoding="utf-8" standalone="yes"?>
<Gesture Name="Deer" Subject="user" InputType="stylus" Speed="MEDIUM" NumPts="128">
	<Stroke index="1">
		<Point X="50" Y="5" T="1746617400000" Pressure="128" />
		<Point X="48.016" Y="5.801" T="1746617400010" Pressure="128" />
		<Point X="46.033" Y="6.603" T="1746617400020" Pressure="128" />
		<Point X="44.049" Y="7.404" T="1746617400030" Pressure="128" />
		<Point X="42.066" Y="8.205" T="1746617400040" Pressure="128" />
		<Point X="40.082" Y="9.007" T="1746617400050" Pressure="128" />
		<Point X="38.099" Y="9.808" T="1746617400060" Pressure="128" />
		<Point X="36.115" Y="10.609" T="1746617400070" Pressure="128" />
		<Point X="34.132" Y="11.411" T="1746617400080" Pressure="128" />
		<Point X="32.148" Y="12.212" T="1746617400090" Pressure="128" />
		<Point X="30.165" Y="13.014" T="1746617400100" Pressure="128" />
		<Point X="28.181" Y="13.815" T="1746617400110" Pressure="128" />
		<Point X="26.198" Y="14.616" T="1746617400120" Pressure="128" />
		<Point X="24.214" Y="15.418" T="1746617400130" Pressure="128" />
		<Point X="22.231" Y="16.219" T="1746617400140" Pressure="128" />
		<Point X="20.247" Y="17.020" T="1746617400150" Pressure="128" />
		<Point X="18.264" Y="17.822" T="1746617400160" Pressure="128" />
		<Point X="16.280" Y="18.623" T="1746617400170" Pressure="128" />
		<Point X="14.297" Y="19.425" T="1746617400180" Pressure="128" />
		<Point X="12.313" Y="20.226" T="1746617400190" Pressure="128" />
		<Point X="10.330" Y="21.027" T="1746617400200" Pressure="128" />
		<Point X="8.346" Y="21.829" T="1746617400210" Pressure="128" />
		<Point X="6.363" Y="22.630" T="1746617400220" Pressure="128" />
		<Point X="5" Y="23" T="1746617400230" Pressure="128" />
		<Point X="5" Y="24.406" T="1746617400240" Pressure="128" />
		<Point X="5" Y="25.812" T="1746617400250" Pressure="128" />
		<Point X="5" Y="27.218" T="1746617400260" Pressure="128" />
		<Point X="5" Y="28.625" T="1746617400270" Pressure="128" />
		<Point X="5" Y="30.031" T="1746617400280" Pressure="128" />
		<Point X="5" Y="31.437" T="1746617400290" Pressure="128" />
		<Point X="5" Y="32.843" T="1746617400300" Pressure="128" />
		<Point X="5" Y="34.250" T="1746617400310" Pressure="128" />
		<Point X="5" Y="35.656" T="1746617400320" Pressure="128" />
		<Point X="5" Y="37.062" T="1746617400330" Pressure="128" />
		<Point X="5" Y="38.468" T="1746617400340" Pressure="128" />
		<Point X="5" Y="39.875" T="1746617400350" Pressure="128" />
		<Point X="5" Y="41.281" T="1746617400360" Pressure="128" />
		<Point X="5" Y="42.687" T="1746617400370" Pressure="128" />
		<Point X="5" Y="44.093" T="1746617400380" Pressure="128" />
		<Point X="5" Y="45.5" T="1746617400390" Pressure="128" />
		<Point X="6.996" Y="46.5" T="1746617400400" Pressure="128" />
		<Point X="8.992" Y="47.5" T="1746617400410" Pressure="128" />
		<Point X="10.988" Y="48.5" T="1746617400420" Pressure="128" />
		<Point X="12.984" Y="49.5" T="1746617400430" Pressure="128" />
		<Point X="14.980" Y="50.5" T="1746617400440" Pressure="128" />
		<Point X="16.976" Y="51.5" T="1746617400450" Pressure="128" />
		<Point X="18.972" Y="52.5" T="1746617400460" Pressure="128" />
		<Point X="20.968" Y="53.5" T="1746617400470" Pressure="128" />
		<Point X="22.964" Y="54.5" T="1746617400480" Pressure="128" />
		<Point X="24.960" Y="55.5" T="1746617400490" Pressure="128" />
		<Point X="26.956" Y="56.5" T="1746617400500" Pressure="128" />
		<Point X="28.952" Y="57.5" T="1746617400510" Pressure="128" />
		<Point X="30.948" Y="58.5" T="1746617400520" Pressure="128" />
		<Point X="32.944" Y="59.5" T="1746617400530" Pressure="128" />
		<Point X="34.94" Y="60.5" T="1746617400540" Pressure="128" />
		<Point X="36.936" Y="61.5" T="1746617400550" Pressure="128" />
		<Point X="38.932" Y="62.5" T="1746617400560" Pressure="128" />
		<Point X="40.928" Y="63.5" T="1746617400570" Pressure="128" />
		<Point X="42.924" Y="64.5" T="1746617400580" Pressure="128" />
		<Point X="44.92" Y="65.5" T="1746617400590" Pressure="128" />
		<Point X="46.916" Y="66.5" T="1746617400600" Pressure="128" />
		<Point X="48.912" Y="67.5" T="1746617400610" Pressure="128" />
		<Point X="50.908" Y="68.5" T="1746617400620" Pressure="128" />
		<Point X="52.904" Y="69.5" T="1746617400630" Pressure="128" />
		<Point X="54.9" Y="70.5" T="1746617400640" Pressure="128" />
		<Point X="56.896" Y="71.5" T="1746617400650" Pressure="128" />
		<Point X="58.892" Y="72.5" T="1746617400660" Pressure="128" />
		<Point X="60.888" Y="73.5" T="1746617400670" Pressure="128" />
		<Point X="62.884" Y="74.5" T="1746617400680" Pressure="128" />
		<Point X="64.88" Y="75.5" T="1746617400690" Pressure="128" />
		<Point X="66.876" Y="76.5" T="1746617400700" Pressure="128" />
		<Point X="68" Y="77.125" T="1746617400710" Pressure="128" />
		<!-- ... -->
		<Point X="68" Y="76.25" T="1746617401260" Pressure="128" />
		<Point X="68" Y="75.375" T="1746617401270" Pressure="128" />
	</Stroke>
</Gesture>
